mcp_assoc_memory/__init__.py
mcp_assoc_memory/__main__.py
mcp_assoc_memory/config.py
mcp_assoc_memory/server.py
mcp_assoc_memory/api/dependencies.py
mcp_assoc_memory/api/error_handling.py
mcp_assoc_memory/api/memory_factory.py
mcp_assoc_memory/api/models/__init__.py
mcp_assoc_memory/api/models/common.py
mcp_assoc_memory/api/models/requests.py
mcp_assoc_memory/api/models/responses.py
mcp_assoc_memory/api/processing/__init__.py
mcp_assoc_memory/api/tools/__init__.py
mcp_assoc_memory/api/tools/export_tools.py
mcp_assoc_memory/api/tools/memory_tools.py
mcp_assoc_memory/api/tools/other_tools.py
mcp_assoc_memory/api/tools/prompt_tools.py
mcp_assoc_memory/api/tools/resource_tools.py
mcp_assoc_memory/api/tools/scope_tools.py
mcp_assoc_memory/api/tools/session_tools.py
mcp_assoc_memory/api/utils/__init__.py
mcp_assoc_memory/api/utils/scope_utils.py
mcp_assoc_memory/core/__init__.py
mcp_assoc_memory/core/association.py
mcp_assoc_memory/core/embedding_service.py
mcp_assoc_memory/core/embedding_validator.py
mcp_assoc_memory/core/memory_manager.py
mcp_assoc_memory/core/memory_manager_admin.py
mcp_assoc_memory/core/memory_manager_associations.py
mcp_assoc_memory/core/memory_manager_core.py
mcp_assoc_memory/core/memory_manager_diversified.py
mcp_assoc_memory/core/memory_manager_search.py
mcp_assoc_memory/core/similarity.py
mcp_assoc_memory/core/singleton_memory_manager.py
mcp_assoc_memory/models/__init__.py
mcp_assoc_memory/models/association.py
mcp_assoc_memory/models/memory.py
mcp_assoc_memory/models/project.py
mcp_assoc_memory/storage/__init__.py
mcp_assoc_memory/storage/base.py
mcp_assoc_memory/storage/database_pool.py
mcp_assoc_memory/storage/graph_store.py
mcp_assoc_memory/storage/metadata_store.py
mcp_assoc_memory/storage/vector_store.py
mcp_assoc_memory/storage/vector_store_new.py
mcp_assoc_memory/utils/__init__.py
mcp_assoc_memory/utils/cache.py
mcp_assoc_memory/utils/logging.py
mcp_assoc_memory/utils/metrics.py
mcp_assoc_memory/utils/validation.py
mcp_assoc_memory-0.1.4.dist-info/licenses/LICENSE
mcp_assoc_memory-0.1.4.dist-info/METADATA
mcp_assoc_memory-0.1.4.dist-info/WHEEL
mcp_assoc_memory-0.1.4.dist-info/entry_points.txt
mcp_assoc_memory-0.1.4.dist-info/top_level.txt
mcp_assoc_memory-0.1.4.dist-info/RECORD
