Metadata-Version: 2.4
Name: mcp-assoc-memory
Version: 0.1.4
Summary: Associative Memory MCP Server for LLMs - Knowledge management system with hierarchical scope organization
Author-email: Makoto Katsumata <mako10k@mk10.org>
License: MIT
Project-URL: Homepage, https://github.com/mako10k/mcp-assoc-memory
Project-URL: Repository, https://github.com/mako10k/mcp-assoc-memory
Project-URL: Documentation, https://github.com/mako10k/mcp-assoc-memory/blob/main/README.md
Project-URL: Issues, https://github.com/mako10k/mcp-assoc-memory/issues
Keywords: mcp,llm,memory,associative,vector,embedding
Classifier: Development Status :: 3 - Alpha
Classifier: Intended Audience :: Developers
Classifier: License :: OSI Approved :: MIT License
Classifier: Programming Language :: Python :: 3
Classifier: Programming Language :: Python :: 3.11
Classifier: Programming Language :: Python :: 3.12
Classifier: Topic :: Software Development :: Libraries :: Python Modules
Classifier: Topic :: Scientific/Engineering :: Artificial Intelligence
Requires-Python: >=3.10
License-File: LICENSE
Requires-Dist: mcp>=1.0.0
Requires-Dist: fastmcp>=2.10.0
Requires-Dist: pydantic>=2.0.0
Requires-Dist: chromadb>=0.4.0
Requires-Dist: openai>=1.0.0
Requires-Dist: sentence-transformers>=2.2.0
Requires-Dist: networkx>=3.0
Requires-Dist: fastapi>=0.104.0
Requires-Dist: uvicorn[standard]>=0.24.0
Requires-Dist: SQLAlchemy>=2.0.0
Requires-Dist: aiosqlite>=0.19.0
Requires-Dist: python-multipart>=0.0.6
Requires-Dist: pyjwt>=2.8.0
Requires-Dist: bcrypt>=4.0.0
Requires-Dist: python-dotenv>=1.0.0
Requires-Dist: jinja2>=3.1.0
Requires-Dist: graphviz>=0.20.0
Requires-Dist: numpy>=1.24.0
Requires-Dist: pandas>=2.0.0
Provides-Extra: dev
Requires-Dist: pytest>=7.0.0; extra == "dev"
Requires-Dist: pytest-asyncio>=0.21.0; extra == "dev"
Requires-Dist: pytest-cov>=4.0.0; extra == "dev"
Requires-Dist: pytest-mock>=3.10.0; extra == "dev"
Requires-Dist: black>=23.0.0; extra == "dev"
Requires-Dist: isort>=5.12.0; extra == "dev"
Requires-Dist: flake8>=6.0.0; extra == "dev"
Requires-Dist: mypy>=1.5.0; extra == "dev"
Requires-Dist: pre-commit>=3.3.0; extra == "dev"
Requires-Dist: httpx>=0.24.0; extra == "dev"
Requires-Dist: websockets>=11.0.0; extra == "dev"
Requires-Dist: bandit>=1.7.0; extra == "dev"
Requires-Dist: safety>=2.3.0; extra == "dev"
Requires-Dist: radon>=6.0.0; extra == "dev"
Requires-Dist: codecov>=2.1.0; extra == "dev"
Provides-Extra: test
Requires-Dist: pytest>=7.0.0; extra == "test"
Requires-Dist: pytest-asyncio>=0.21.0; extra == "test"
Requires-Dist: pytest-cov>=4.0.0; extra == "test"
Requires-Dist: pytest-mock>=3.10.0; extra == "test"
Requires-Dist: httpx>=0.24.0; extra == "test"
Requires-Dist: websockets>=11.0.0; extra == "test"
Provides-Extra: production
Requires-Dist: psycopg2-binary>=2.9.0; extra == "production"
Requires-Dist: redis>=4.5.0; extra == "production"
Requires-Dist: prometheus-client>=0.17.0; extra == "production"
Dynamic: license-file
